PySideJZ/JZAbvs.py
PySideJZ/JZButtons.py
PySideJZ/JZComboBox.py
PySideJZ/JZConsts.py
PySideJZ/JZContainer.py
PySideJZ/JZDisplay.py
PySideJZ/JZGroupBox.py
PySideJZ/JZLabel.py
PySideJZ/JZLine.py
PySideJZ/JZLogger.py
PySideJZ/JZMedia.py
PySideJZ/JZSlider.py
PySideJZ/JZSpinBox.py
PySideJZ/JZStatusBar.py
PySideJZ/JZStylesheet.py
PySideJZ/JZTabWidget.py
PySideJZ/JZToolBar.py
PySideJZ/JZWorker.py
PySideJZ/JZtypes.py
PySideJZ/__init__.py
PySideJZ/stylesheet_combinator.py
PySideJZ/stylesheet_generator.py
PySideJZ/__pycache__/JZAbvs.cpython-312.pyc
PySideJZ/__pycache__/JZButtons.cpython-312.pyc
PySideJZ/__pycache__/JZComboBox.cpython-312.pyc
PySideJZ/__pycache__/JZConsts.cpython-312.pyc
PySideJZ/__pycache__/JZContainer.cpython-312.pyc
PySideJZ/__pycache__/JZDisplay.cpython-312.pyc
PySideJZ/__pycache__/JZGroupBox.cpython-312.pyc
PySideJZ/__pycache__/JZLabel.cpython-312.pyc
PySideJZ/__pycache__/JZLine.cpython-312.pyc
PySideJZ/__pycache__/JZLogger.cpython-312.pyc
PySideJZ/__pycache__/JZSlider.cpython-312.pyc
PySideJZ/__pycache__/JZSpinBox.cpython-312.pyc
PySideJZ/__pycache__/JZStatusBar.cpython-312.pyc
PySideJZ/__pycache__/JZStylesheet.cpython-312.pyc
PySideJZ/__pycache__/JZToolBar.cpython-312.pyc
PySideJZ/__pycache__/JZWorker.cpython-312.pyc
PySideJZ/__pycache__/JZtypes.cpython-312.pyc
PySideJZ/__pycache__/__init__.cpython-312.pyc
PySideJZ/__pycache__/stylesheet_generator.cpython-312.pyc
PySideJZ/__pycache__/types.cpython-312.pyc
PySideJZ/stylesheet/CODE_OF_CONDUCT.md
PySideJZ/stylesheet/ISSUES.md
PySideJZ/stylesheet/LICENSE.md
PySideJZ/stylesheet/README.md
PySideJZ/stylesheet/Test Coverage.md
PySideJZ/stylesheet/__init__.py
PySideJZ/stylesheet/base_stylesheet.qss.in
PySideJZ/stylesheet/configure.py
PySideJZ/stylesheet/generate_stylesheet.py
PySideJZ/stylesheet/stylesheet.py
PySideJZ/stylesheet/__pycache__/__init__.cpython-312.pyc
PySideJZ/stylesheet/__pycache__/stylesheet.cpython-312.pyc
PySideJZ/stylesheet/dist/qrc/breeze.qrc
pysidejz-0.1.0rc4.dist-info/METADATA
pysidejz-0.1.0rc4.dist-info/WHEEL
pysidejz-0.1.0rc4.dist-info/entry_points.txt
pysidejz-0.1.0rc4.dist-info/top_level.txt
pysidejz-0.1.0rc4.dist-info/RECORD
