Metadata-Version: 2.4
Name: PySideJZ
Version: 0.1.0rc4
Summary: Package of prefabricated custom PySide6 widgets
Author-email: Jokubas Ziziunas <jokubas0001@gmail.com>
Requires-Python: <3.14,>=3.12
Requires-Dist: PySide6==6.9.0
Requires-Dist: loguru==0.7.3
Requires-Dist: qtawesome==1.4.0
Requires-Dist: pyudev==0.24.3
Requires-Dist: pyserial==3.5
Provides-Extra: display
Requires-Dist: numpy==2.2.6; extra == "display"
